farbprinter/__init__.py
farbprinter/farbprinter.py
farbprinter-0.0.2.1.dist-info/METADATA
farbprinter-0.0.2.1.dist-info/WHEEL
farbprinter-0.0.2.1.dist-info/top_level.txt
farbprinter-0.0.2.1.dist-info/RECORD
